Workbook
Name Slicer_Month: #N/A

Sheet Records
B2: Income & Expense
B4: Date | C4: Month | D4: Amount | E4: Item | F4: Category | G4: Remark
B5: 45658 | C5: =TEXT(Table1[[#This Row],[Date]],"MMMM") -> January | D5: 35000 | E5: Salary | F5: =VLOOKUP(Table1[[#This Row],[Item ]],Table2[],2,) -> Income
B6: 45660 | C6: =TEXT(Table1[[#This Row],[Date]],"MMMM") -> January | D6: 600 | E6: Fuel | F6: =VLOOKUP(Table1[[#This Row],[Item ]],Table2[],2,) -> Expense
B7: 45660 | C7: =TEXT(Table1[[#This Row],[Date]],"MMMM") -> January | D7: 250 | E7: Entertainment | F7: =VLOOKUP(Table1[[#This Row],[Item ]],Table2[],2,) -> Expense | K7: Item | L7: Category
B8: 45667 | C8: =TEXT(Table1[[#This Row],[Date]],"MMMM") -> January | D8: 3600 | E8: Shopping | F8: =VLOOKUP(Table1[[#This Row],[Item ]],Table2[],2,) -> Expense | K8: Salary | L8: Income
B9: 45668 | C9: =TEXT(Table1[[#This Row],[Date]],"MMMM") -> January | D9: 8000 | E9: Food | F9: =VLOOKUP(Table1[[#This Row],[Item ]],Table2[],2,) -> Expense | K9: Rent Income | L9: Income
B10: 45669 | C10: =TEXT(Table1[[#This Row],[Date]],"MMMM") -> January | D10: 3000 | E10: Health | F10: =VLOOKUP(Table1[[#This Row],[Item ]],Table2[],2,) -> Expense | K10: Shopping | L10: Expense
B11: 45676 | C11: =TEXT(Table1[[#This Row],[Date]],"MMMM") -> January | D11: 1000 | E11: Entertainment | F11: =VLOOKUP(Table1[[#This Row],[Item ]],Table2[],2,) -> Expense | K11: Food | L11: Expense
B12: 45689 | C12: =TEXT(Table1[[#This Row],[Date]],"MMMM") -> February | D12: 35000 | E12: Salary | F12: =VLOOKUP(Table1[[#This Row],[Item ]],Table2[],2,) -> Income | K12: Fuel | L12: Expense
B13: 45691 | C13: =TEXT(Table1[[#This Row],[Date]],"MMMM") -> February | D13: 8500 | E13: Food | F13: =VLOOKUP(Table1[[#This Row],[Item ]],Table2[],2,) -> Expense | K13: Transpotation | L13: Expense
B14: 45698 | C14: =TEXT(Table1[[#This Row],[Date]],"MMMM") -> February | D14: 10000 | E14: Shopping | F14: =VLOOKUP(Table1[[#This Row],[Item ]],Table2[],2,) -> Expense | K14: Health | L14: Expense
B15: 45710 | C15: =TEXT(Table1[[#This Row],[Date]],"MMMM") -> February | D15: 1000 | E15: Fuel | F15: =VLOOKUP(Table1[[#This Row],[Item ]],Table2[],2,) -> Expense | K15: Entertainment | L15: Expense
B16: 45716 | C16: =TEXT(Table1[[#This Row],[Date]],"MMMM") -> February | D16: 2000 | E16: Transpotation | F16: =VLOOKUP(Table1[[#This Row],[Item ]],Table2[],2,) -> Expense
B17: 45718 | C17: =TEXT(Table1[[#This Row],[Date]],"MMMM") -> March | D17: 32000 | E17: Salary | F17: =VLOOKUP(Table1[[#This Row],[Item ]],Table2[],2,) -> Income
B18: 45726 | C18: =TEXT(Table1[[#This Row],[Date]],"MMMM") -> March | D18: 8500 | E18: Food | F18: =VLOOKUP(Table1[[#This Row],[Item ]],Table2[],2,) -> Expense
B19: 45727 | C19: =TEXT(Table1[[#This Row],[Date]],"MMMM") -> March | D19: 400 | E19: Transpotation | F19: =VLOOKUP(Table1[[#This Row],[Item ]],Table2[],2,) -> Expense
B20: 45727 | C20: =TEXT(Table1[[#This Row],[Date]],"MMMM") -> March | D20: 500 | E20: Entertainment | F20: =VLOOKUP(Table1[[#This Row],[Item ]],Table2[],2,) -> Expense
B21: 45731 | C21: =TEXT(Table1[[#This Row],[Date]],"MMMM") -> March | D21: 2000 | E21: Rent Income | F21: =VLOOKUP(Table1[[#This Row],[Item ]],Table2[],2,) -> Income
B22: 45736 | C22: =TEXT(Table1[[#This Row],[Date]],"MMMM") -> March | D22: 3000 | E22: Shopping | F22: =VLOOKUP(Table1[[#This Row],[Item ]],Table2[],2,) -> Expense
B23: 45739 | C23: =TEXT(Table1[[#This Row],[Date]],"MMMM") -> March | D23: 1575 | E23: Fuel | F23: =VLOOKUP(Table1[[#This Row],[Item ]],Table2[],2,) -> Expense
B24: 45739 | C24: =TEXT(Table1[[#This Row],[Date]],"MMMM") -> March | D24: 2000 | E24: Fuel | F24: =VLOOKUP(Table1[[#This Row],[Item ]],Table2[],2,) -> Expense
B25: 45749 | C25: =TEXT(Table1[[#This Row],[Date]],"MMMM") -> April | D25: 35000 | E25: Salary | F25: =VLOOKUP(Table1[[#This Row],[Item ]],Table2[],2,) -> Income
B26: 45752 | C26: =TEXT(Table1[[#This Row],[Date]],"MMMM") -> April | D26: 1200 | E26: Food | F26: =VLOOKUP(Table1[[#This Row],[Item ]],Table2[],2,) -> Expense
B27: 45756 | C27: =TEXT(Table1[[#This Row],[Date]],"MMMM") -> April | D27: 2800 | E27: Fuel | F27: =VLOOKUP(Table1[[#This Row],[Item ]],Table2[],2,) -> Expense
... B86: 45998 | C86: =TEXT(Table1[[#This Row],[Date]],"MMMM") -> December | D86: 8500 | E86: Food | F86: =VLOOKUP(Table1[[#This Row],[Item ]],Table2[],2,) -> Expense

Sheet Dashboard 2

Sheet Dashboard
B2: Personal Finance Dashboard
B4: YTD Income | C4: =SUM(C9:C200) -> 477154.17 | E4: YTD Expense | F4: =SUM(F9:F20) -> 223425 | H4: YTD Savings | I4: =SUM(I9:I20) -> 217025
B6: Income & Expense - Monthly Breakdown
B8: Income | E8: Expense | H8: Savings | L8: Income & Exspense -Item wise Breakdown
B9: January | C9: =SUMIFS(Table1[Amount],Table1[Month],Dashboard!B9,Table1[Category],"Income") -> 35000 | E9: January | F9: =SUMIFS(Table1[Amount],Table1[Month],Dashboard!E9,Table1[Category],"Expense") -> 16450 | H9: January | I9: =C9-F9 -> 18550
B10: February | C10: =SUMIFS(Table1[Amount],Table1[Month],Dashboard!B10,Table1[Category],"Income") -> 35000 | E10: February | F10: =SUMIFS(Table1[Amount],Table1[Month],Dashboard!E10,Table1[Category],"Expense") -> 21500 | H10: February | I10: =C10-F10 -> 13500 | L10: Income | O10: Expense
B11: March | C11: =SUMIFS(Table1[Amount],Table1[Month],Dashboard!B11,Table1[Category],"Income") -> 34000 | E11: March | F11: =SUMIFS(Table1[Amount],Table1[Month],Dashboard!E11,Table1[Category],"Expense") -> 15975 | H11: March | I11: =C11-F11 -> 18025 | L11: Salary | M11: =SUMIF(Table1[[Item ]],Dashboard!L11,Table1[Amount]) -> 429500 | O11: Shopping | P11: =SUMIF(Records!E5:E86,Dashboard!O11,Records!D5:D86) -> 41200
B12: April | C12: =SUMIFS(Table1[Amount],Table1[Month],Dashboard!B12,Table1[Category],"Income") -> 36900 | E12: April | F12: =SUMIFS(Table1[Amount],Table1[Month],Dashboard!E12,Table1[Category],"Expense") -> 13100 | H12: April | I12: =C12-F12 -> 23800 | L12: Rent Income | M12: =SUMIF(Table1[[Item ]],Dashboard!L12,Table1[Amount]) -> 10950 | O12: Food | P12: =SUMIF(Records!E6:E83,Dashboard!O12,Records!D6:D83) -> 77700
B13: May | C13: =SUMIFS(Table1[Amount],Table1[Month],Dashboard!B13,Table1[Category],"Income") -> 35000 | E13: May | F13: =SUMIFS(Table1[Amount],Table1[Month],Dashboard!E13,Table1[Category],"Expense") -> 22100 | H13: May | I13: =C13-F13 -> 12900 | O13: Fuel | P13: =SUMIF(Records!E7:E84,Dashboard!O13,Records!D7:D84) -> 17675
B14: June | C14: =SUMIFS(Table1[Amount],Table1[Month],Dashboard!B14,Table1[Category],"Income") -> 35000 | E14: June | F14: =SUMIFS(Table1[Amount],Table1[Month],Dashboard!E14,Table1[Category],"Expense") -> 20400 | H14: June | I14: =C14-F14 -> 14600 | O14: Transpotation | P14: =SUMIF(Records!E8:E85,Dashboard!O14,Records!D8:D85) -> 23900
B15: July | C15: =SUMIFS(Table1[Amount],Table1[Month],Dashboard!B15,Table1[Category],"Income") -> 35000 | E15: July | F15: =SUMIFS(Table1[Amount],Table1[Month],Dashboard!E15,Table1[Category],"Expense") -> 25200 | H15: July | I15: =C15-F15 -> 9800 | O15: Health | P15: =SUMIF(Records!E9:E86,Dashboard!O15,Records!D9:D86) -> 21400
B16: August | C16: =SUMIFS(Table1[Amount],Table1[Month],Dashboard!B16,Table1[Category],"Income") -> 38300 | E16: August | F16: =SUMIFS(Table1[Amount],Table1[Month],Dashboard!E16,Table1[Category],"Expense") -> 24900 | H16: August | I16: =C16-F16 -> 13400 | O16: Entertainment | P16: =SUMIF(Records!E10:E87,Dashboard!O16,Records!D10:D87) -> 24200
B17: September | C17: =SUMIFS(Table1[Amount],Table1[Month],Dashboard!B17,Table1[Category],"Income") -> 38250 | E17: September | F17: =SUMIFS(Table1[Amount],Table1[Month],Dashboard!E17,Table1[Category],"Expense") -> 26000 | H17: September | I17: =C17-F17 -> 12250
B18: October | C18: =SUMIFS(Table1[Amount],Table1[Month],Dashboard!B18,Table1[Category],"Income") -> 43000 | E18: October | F18: =SUMIFS(Table1[Amount],Table1[Month],Dashboard!E18,Table1[Category],"Expense") -> 21300 | H18: October | I18: =C18-F18 -> 21700
B19: November | C19: =SUMIFS(Table1[Amount],Table1[Month],Dashboard!B19,Table1[Category],"Income") -> 37000 | E19: November | F19: =SUMIFS(Table1[Amount],Table1[Month],Dashboard!E19,Table1[Category],"Expense") -> 8000 | H19: November | I19: =C19-F19 -> 29000
B20: December | C20: =SUMIFS(Table1[Amount],Table1[Month],Dashboard!B20,Table1[Category],"Income") -> 38000 | E20: December | F20: =SUMIFS(Table1[Amount],Table1[Month],Dashboard!E20,Table1[Category],"Expense") -> 8500 | H20: December | I20: =C20-F20 -> 29500
B21: Average | C21: =AVERAGEIF(C9:C20,">0") -> 36704.167 | E21: Average | F21: =AVERAGEIF(F9:F20,">0") -> 18618.75 | H21: Average | I21: =AVERAGEIF(I9:I20,">0") -> 18085.417
F25: ="TOTAL INCOME" & CHAR(10) & "₹ " & TEXT(C4,"#,##0") -> TOTAL INCOME ₹ 4,77,154
F26: ="TOTAL EXPENSE" & CHAR(10) & "₹ " & TEXT(F4,"#,##0") -> TOTAL EXPENSE ₹ 2,23,425
F27: ="NET SAVINGS"& CHAR(10) & "₹ " & TEXT(I4,"#,##0") -> NET SAVINGS ₹ 2,17,025

Sheet Pivot
A1: Category | B1: Income | D1: Category | E1: Expense
A3: Total Income | B3: Total | D3: Total Expense | E3: Total
A4: Total | B4: 440450 | D4: Total | E4: 223425 | J4: Category | K4: Expense | M4: Sum of Amount | N4: Category
M5: Month | N5: Expense | O5: Income | P5: Grand Total
J6: Item wise Expense | M6: January | N6: 16450 | O6: 35000 | P6: 51450 | R6: ="Entertainment" & CHAR(10) & "₹ " & TEXT(GETPIVOTDATA("Amount",$J$6,"Item ","Entertainment"),"#,##0") -> Entertainment ₹ 24,450
J7: Item | K7: Total | M7: February | N7: 21500 | O7: 35000 | P7: 56500 | R7: ="Food" & CHAR(10) & "₹ " & TEXT(GETPIVOTDATA("Amount",$J$6,"Item ","Food"),"#,##0") -> Food ₹ 94,200
J8: Entertainment | K8: 24450 | M8: March | N8: 15975 | O8: 34000 | P8: 49975 | R8: ="Fuel" & CHAR(10) & "₹ " & TEXT(GETPIVOTDATA("Amount",$J$6,"Item ","Fuel"),"#,##0") -> Fuel ₹ 18,275
J9: Food | K9: 94200 | M9: April | N9: 13100 | O9: 36900 | P9: 50000 | R9: ="Health" & CHAR(10) & "₹ " & TEXT(GETPIVOTDATA("Amount",$J$6,"Item ","Health"),"#,##0") -> Health ₹ 21,400
J10: Fuel | K10: 18275 | M10: May | N10: 22100 | O10: 35000 | P10: 57100 | R10: ="Shopping" & CHAR(10) & "₹ " & TEXT(GETPIVOTDATA("Amount",$J$6,"Item ","Shopping"),"#,##0") -> Shopping ₹ 41,200
J11: Health | K11: 21400 | M11: June | N11: 20400 | O11: 35000 | P11: 55400 | R11: ="Transportaion" & CHAR(10) & "₹ " & TEXT(GETPIVOTDATA("Amount",$J$6,"Item ","Transpotation"),"#,##0") -> Transportaion ₹ 23,900
J12: Shopping | K12: 41200 | M12: July | N12: 25200 | O12: 35000 | P12: 60200
J13: Transpotation | K13: 23900 | M13: August | N13: 24900 | O13: 38300 | P13: 63200
J14: Grand Total | K14: 223425 | M14: September | N14: 26000 | O14: 38250 | P14: 64250
M15: October | N15: 21300 | O15: 43000 | P15: 64300
M16: November | N16: 8000 | O16: 37000 | P16: 45000
M17: December | N17: 8500 | O17: 38000 | P17: 46500
M18: Grand Total | N18: 223425 | O18: 440450 | P18: 663875
M20: Month | N20: (All)
J21: Category | K21: Income
M22: Sum of Amount
J23: Income Sources | M23: Category | N23: Total
J24: Item | K24: Total | M24: Expense | N24: 223425
J25: Rent Income | K25: 10950 | M25: Income | N25: 440450
J26: Salary | K26: 429500 | M26: Grand Total | N26: 663875
J27: Grand Total | K27: 440450

Sheet Detail1
A1: Details for Sum of Amount - Month: July, Category: Expense
A3: Date | B3: Month | C3: Amount | D3: Item | E3: Category | F3: Remark
A4: 45869 | B4: July | C4: 1800 | D4: Shopping | E4: Expense
A5: 45867 | B5: July | C5: 2700 | D5: Shopping | E5: Expense
A6: 45860 | B6: July | C6: 2300 | D6: Fuel | E6: Expense
A7: 45860 | B7: July | C7: 3100 | D7: Shopping | E7: Expense
A8: 45856 | B8: July | C8: 3900 | D8: Health | E8: Expense
A9: 45851 | B9: July | C9: 2500 | D9: Entertainment | E9: Expense
A10: 45848 | B10: July | C10: 700 | D10: Fuel | E10: Expense
A11: 45843 | B11: July | C11: 8200 | D11: Food | E11: Expense
